{
  "extractor": {
    "host": "54.213.112.104:8080",
    "apiVersion": "v1",
    "apiKey": "8742b79d-08d7-4e1b-a4ce-27b4817348a1",
    "url": "",
    "userName": "admin",
    "password": "123"
  },
  "validator": {
    "host": "54.213.112.104:8080",
    "apiVersion": "v1",
    "apiKey": "90620cc1-1d18-4ba1-a6cf-f8e17d351d16",
    "url": "",
    "userName": "admin",
    "password": "123"
  },
  "relyingparty": {
    "host": "54.213.112.104:8080",
    "apiVersion": "v1",
    "apiKey": "e489e5ce-e80a-4334-8864-abfa86e6014c",
    "url": "",
    "userName": "admin",
    "password": "123"
  },
  "owner": {
    "host": "54.213.112.104:8080",
    "apiVersion": "v1",
    "apiKey": "8742b79d-08d7-4e1b-a4ce-27b4817348a1",
    "url": "",
    "userName": "admin",
    "password": "123"
  }

}